wcd/__init__.py
wcd/__main__.py
wcd/__version__.py
wcd/cfg.py
wcd/default-cfg.yml
wcd/event.py
wcd/funcs.py
wcd/trace.py
wcd/wcc.py
wcd/wcd.py
wcd/wp_cache.py
wcd-0.1.0.dist-info/LICENSE
wcd-0.1.0.dist-info/METADATA
wcd-0.1.0.dist-info/WHEEL
wcd-0.1.0.dist-info/entry_points.txt
wcd-0.1.0.dist-info/RECORD
