Metadata-Version: 2.1
Name: wcd
Version: 0.1.0
Summary: 'Wallpaper changing daemon' is exactly what its name suggests. It tries to be the 'mpd' of wallpapers.
Home-page: https://github.com/brunofauth/wcd
License: MIT
Keywords: wallpaper
Author: Bruno Fauth
Author-email: 149593@upf.br
Requires-Python: >=3.7,<4.0
Classifier: License :: OSI Approved :: MIT License
Classifier: Operating System :: OS Independent
Classifier: Programming Language :: Python :: 3
Classifier: Programming Language :: Python :: 3.7
Classifier: Programming Language :: Python :: 3.8
Classifier: Programming Language :: Python :: 3.9
Classifier: Programming Language :: Python :: 3.10
Classifier: Programming Language :: Python :: 3.11
Classifier: Programming Language :: Python :: 3
Requires-Dist: PyYAML (>=6.0,<7.0)
Requires-Dist: coloredlogs (>=15.0,<16.0)
Requires-Dist: humanfriendly (>=10.0,<11.0)
Project-URL: Bug Tracker, https://github.com/brunofauth/wcd/issues
Project-URL: Repository, https://github.com/brunofauth/wcd
